setup.py
distributions_g111/Binomialdistribution.py
distributions_g111/Gaussiandistribution.py
distributions_g111/Generaldistribution.py
distributions_g111/__init__.py
distributions_g111.egg-info/PKG-INFO
distributions_g111.egg-info/SOURCES.txt
distributions_g111.egg-info/dependency_links.txt
distributions_g111.egg-info/not-zip-safe
distributions_g111.egg-info/top_level.txt